README.txt
setup.cfg
setup.py
edeposit/__init__.py
edeposit.app.fields.egg-info/PKG-INFO
edeposit.app.fields.egg-info/SOURCES.txt
edeposit.app.fields.egg-info/dependency_links.txt
edeposit.app.fields.egg-info/entry_points.txt
edeposit.app.fields.egg-info/namespace_packages.txt
edeposit.app.fields.egg-info/not-zip-safe
edeposit.app.fields.egg-info/requires.txt
edeposit.app.fields.egg-info/top_level.txt
edeposit/app/__init__.py
edeposit/app/fields/__init__.py
edeposit/app/fields/_fields.py
edeposit/app/fields/interfaces.py
edeposit/app/fields/isbn.py
edeposit/app/fields/tests.py
edeposit/app/fields/utils.py