Metadata-Version: 1.1
Name: edeposit.app.fields
Version: 1.0.0
Summary: Custom Plone fields and widgets for eDeposit project
Home-page: https://github.com/edeposit/edeposit.app.fields
Author: Jan Stavěl
Author-email: stavel.jan@gmail.com
License: GPL
Platform: UNKNOWN
Classifier: Framework :: Plone
Classifier: Programming Language :: Python
